apkid/__init__.py
apkid/apkid.py
apkid/main.py
apkid/output.py
apkid/rules.py
apkid/rules/rules.yarc
apkid-3.0.0.dist-info/AUTHORS.txt
apkid-3.0.0.dist-info/LICENSE.COMMERCIAL
apkid-3.0.0.dist-info/LICENSE.GPL
apkid-3.0.0.dist-info/METADATA
apkid-3.0.0.dist-info/WHEEL
apkid-3.0.0.dist-info/entry_points.txt
apkid-3.0.0.dist-info/top_level.txt
apkid-3.0.0.dist-info/RECORD
